padar_realtime/__init__.py
padar_realtime/input_stream.py
padar_realtime/metawear_stream.py
padar_realtime/processor_stream.py
padar_realtime/stream_package.py
padar_realtime-1.4.2.dist-info/METADATA
padar_realtime-1.4.2.dist-info/RECORD
padar_realtime-1.4.2.dist-info/WHEEL
padar_realtime-1.4.2.dist-info/top_level.txt
