Metadata-Version: 2.1
Name: padar-realtime
Version: 1.4.2
Summary: Real-time engine used to process and visualize accelerometer data for padar package
Home-page: UNKNOWN
Author: UNKNOWN
Author-email: UNKNOWN
License: UNKNOWN
Platform: UNKNOWN
Requires-Dist: websockets
Requires-Dist: flask
Requires-Dist: arrow
Requires-Dist: pymetawear
Requires-Dist: pandas
Requires-Dist: metawear
Requires-Dist: warble
